{
    "fechaDescarga": "05/01/2021, 10:52:09",
    "json_original": {
        "tipoNorma": "Ley",
        "nroNorma": "19889",
        "anioNorma": 2020,
        "nombreNorma": "APROBACION DE LA LEY DE URGENTE CONSIDERACION. LUC. LEY DE URGENCIA",
        "leyenda": " Documento Actualizado ",
        "urlTodaLaNorma": "/bases/leyes/19889-2020",
        "fechaPromulgacion": "09/07/2020",
        "fechaPublicacion": "14/07/2020",
        "tituloArticulo": "  SECCI\u00d3N III - EDUCACI\u00d3N  ",
        "nombreArticulo": "Art\u00edculo 158 ",
        "textoArticulo": "    (Cometidos de las Direcciones Generales y del Consejo de Formaci\u00f3n en Educaci\u00f3n).- \r\n\r\n   (*)\r\n ",
        "notasArticulo": "<b><font color=\"#0000FF\">Este art\u00edculo dio nueva redacci\u00f3n a:</font></b> Ley N\u00ba 18.437 de 12/12/2008 art\u00edculo \r\n<a href=\"/bases/leyes/18437-2008/63\" >63</a>.\r\n"
    },
    "numeroArticulo": "158",
    "seccionArticulo": "III",
    "capituloArticulo": null,
    "textoArticulo": " (Cometidos de las Direcciones Generales y del Consejo de Formaci\u00f3n en Educaci\u00f3n).- (*) ",
    "notasArticulo": "Este art\u00edculo dio nueva redacci\u00f3n a: Ley N\u00ba 18.437 de 12/12/2008 art\u00edculo 63. ",
    "textoOriginal": " (Cometidos de los Consejos).- Compete a los Consejos de Educaci\u00f3n: A) Desarrollar los procesos de ense\u00f1anza y aprendizaje correspondientes a su respectivo nivel educativo. B) Aprobar los planes de estudio y los programas de las asignaturas que ellos incluyan. C) Administrar los servicios y dependencias a su cargo. D) Supervisar el desarrollo de los planes, programas y cursos. E) Reglamentar la organizaci\u00f3n y el funcionamiento de los servicios a su cargo y adoptar las medidas que los mismos requieran. F) Proyectar los presupuestos de sueldos, gastos e inversiones correspondientes al nivel educativo asignado y sus modificaciones, as\u00ed como las rendiciones de cuentas y balances de ejecuci\u00f3n presupuestal correspondientes a los servicios a su cargo. G) Realizar toda clase de nombramientos, reelecciones, ascensos y sanciones, as\u00ed como otorgar licencias y designar el personal docente y no docente, conforme al Estatuto del Funcionario y a las ordenanzas que apruebe el Consejo Directivo Central. Podr\u00e1n tambi\u00e9n dictar normas en esta materia con arreglo al estatuto y a las ordenanzas. H) Proponer al Consejo Directivo Central de la ANEP la destituci\u00f3n del personal docente o no docente a su cargo, por razones de ineptitud, omisi\u00f3n o delito con las garant\u00edas que fija la ley y el estatuto respectivo. I) Designar al Secretario General de cada Consejo, con car\u00e1cter de cargo de particular confianza, quien deber\u00e1 haber sido funcionario del ente por un lapso no menor a diez a\u00f1os. J) Proyectar las normas estatutarias que crea necesarias para sus funcionarios y elevarlas al Consejo Directivo Central a los efectos de su aprobaci\u00f3n e incorporaci\u00f3n al Estatuto de los Funcionarios del ente. K) Habilitar, autorizar, supervisar y fiscalizar los institutos del nivel educativo correspondiente, en consonancia con los lineamientos aprobados por el Consejo Directivo Central. L) Conferir y revalidar certificados de estudio nacionales y revalidar certificados de estudio extranjeros en los niveles y modalidades de educaci\u00f3n a su cargo. M) Adoptar las resoluciones atinentes al \u00e1mbito de su competencia, salvo aquellas que por la Constituci\u00f3n de la Rep\u00fablica, la presente ley y las ordenanzas correspondan a los dem\u00e1s \u00f3rganos. N) Verificar en el caso de los Consejos de Educaci\u00f3n Media B\u00e1sica, Educaci\u00f3n Media Superior y Educaci\u00f3n T\u00e9cnica-Profesional (UTU), la aprobaci\u00f3n o validaci\u00f3n en su caso del nivel anterior, as\u00ed como habilitar para cursar los niveles educativos superiores correspondiente. O) Promover un clima de participaci\u00f3n democr\u00e1tica y propiciar en forma permanente una reflexi\u00f3n cr\u00edtica y responsable, en todo el \u00e1mbito de la instituci\u00f3n a su cargo. P) Ejercer las dem\u00e1s atribuciones que le delegare especialmente el Consejo Directivo Central. ",
    "textoModificado": " (Cometidos de las Direcciones Generales y del Consejo de Formaci\u00f3n en Educaci\u00f3n).- Compete a las Direcciones Generales y al Consejo de Formaci\u00f3n en Educaci\u00f3n: A) Desarrollar los procesos de ense\u00f1anza y aprendizaje correspondientes a su respectivo nivel educativo. B) Elaborar los planes de estudio y los programas de las asignaturas que ellos incluyan y presentarlos al Consejo Directivo Central de la Administraci\u00f3n Nacional de Educaci\u00f3n P\u00fablica (ANEP) para su aprobaci\u00f3n. C) Administrar los servicios y dependencias a su cargo. D) Supervisar el desarrollo de los planes, programas y cursos. E) Reglamentar la organizaci\u00f3n y el funcionamiento de los servicios a su cargo y adoptar las medidas que los mismos requieran. F) Proyectar los presupuestos de sueldos, gastos e inversiones correspondientes al nivel educativo asignado y sus modificaciones, as\u00ed como las rendiciones de cuentas y balances de ejecuci\u00f3n presupuestal correspondientes a los servicios a su cargo. G) Realizar nombramientos, reelecciones, ascensos y sanciones, as\u00ed como otorgar licencias y designar el personal docente y no docente, conforme al Estatuto del Funcionario y a las ordenanzas que apruebe el Consejo Directivo Central. Podr\u00e1n tambi\u00e9n dictar normas en esta materia con arreglo al estatuto y a las ordenanzas. H) Proponer al Consejo Directivo Central de la ANEP la destituci\u00f3n del personal docente o no docente a su cargo, por razones de ineptitud, omisi\u00f3n o delito con las garant\u00edas que fija la ley y el estatuto respectivo. I) Designar al Secretario General de cada subsistema, con car\u00e1cter de cargo de particular confianza. J) Proyectar las normas estatutarias que crea necesarias para sus funcionarios y elevarlas al Consejo Directivo Central a los efectos de su aprobaci\u00f3n e incorporaci\u00f3n a los estatutos de funcionarios del ente. K) Habilitar, autorizar, supervisar y fiscalizar los institutos del nivel educativo correspondiente, en consonancia con la Constituci\u00f3n de la Rep\u00fablica, la ley y los lineamientos aprobados por el Consejo Directivo Central. L) Conferir y revalidar certificados de estudio nacionales, y reconocer los certificados de estudio extranjeros requeridos como condici\u00f3n de acceso para los niveles y modalidades de educaci\u00f3n a su cargo. M) Adoptar las resoluciones atinentes al \u00e1mbito de su competencia, salvo aquellas que, por la Constituci\u00f3n de la Rep\u00fablica, la presente ley y las ordenanzas, correspondan a los dem\u00e1s \u00f3rganos. N) Verificar la aprobaci\u00f3n o validaci\u00f3n del nivel educativo anterior, as\u00ed como habilitar para cursar los niveles educativos superiores cuando correspondiere. O) Promover un clima de participaci\u00f3n democr\u00e1tica y propiciar en forma permanente una reflexi\u00f3n cr\u00edtica y responsable, en todo el \u00e1mbito de la instituci\u00f3n a su cargo. P) Ejercer las dem\u00e1s atribuciones que le delegare especialmente el Consejo Directivo Central. (*) "
}