{
    "json_original": {
        "tipoNorma": "Ley",
        "nroNorma": "19889",
        "anioNorma": 2020,
        "nombreNorma": "APROBACION DE LA LEY DE URGENTE CONSIDERACION. LUC. LEY DE URGENCIA",
        "leyenda": " Documento Actualizado ",
        "urlTodaLaNorma": "/bases/leyes/19889-2020",
        "fechaPromulgacion": "09/07/2020",
        "fechaPublicacion": "14/07/2020",
        "tituloArticulo": "  SECCI\u00d3N III - EDUCACI\u00d3N  ",
        "nombreArticulo": "Art\u00edculo 186 ",
        "textoArticulo": "    (Cometidos).- \r\n\r\n   (*)\r\n ",
        "notasArticulo": "<b><font color=\"#0000FF\">Este art\u00edculo dio nueva redacci\u00f3n a:</font></b> Ley N\u00ba 18.437 de 12/12/2008 art\u00edculo \r\n<a href=\"/bases/leyes/18437-2008/108\" >108</a>.\r\n"
    },
    "numeroArticulo": "186",
    "seccionArticulo": "III",
    "capituloArticulo": null,
    "textoArticulo": " (Cometidos).- (*) ",
    "notasArticulo": "Este art\u00edculo dio nueva redacci\u00f3n a: Ley N\u00ba 18.437 de 12/12/2008 art\u00edculo 108. ",
    "textoOriginal": " (Cometidos).- A la Comisi\u00f3n Coordinadora del Sistema Nacional de la Educaci\u00f3n P\u00fablica le compete: A) Velar por el cumplimiento de los fines y principios establecidos en la presente ley. B) Coordinar, concertar y emitir opini\u00f3n sobre las pol\u00edticas educativas de la educaci\u00f3n p\u00fablica e impartir recomendaciones a los entes. C) Promover la planificaci\u00f3n de la educaci\u00f3n p\u00fablica. D) Cumplir con los cometidos expresamente se\u00f1alados en la presente ley. E) Promover la aplicaci\u00f3n de los principios, fines y orientaciones generales que emanan de la presente ley. F) Convocar al Congreso Nacional de Educaci\u00f3n. G) Conformar comisiones de asesoramiento y estudio de distintas tem\u00e1ticas educativas. ",
    "textoModificado": " (Cometidos).- A la Comisi\u00f3n Coordinadora de la Educaci\u00f3n le compete: A) Velar por el cumplimiento de los fines y principios establecidos en la presente ley. B) Coordinar, concertar y emitir opini\u00f3n sobre las pol\u00edticas educativas. C) Promover la planificaci\u00f3n de la acci\u00f3n educativa. D) Promover la aplicaci\u00f3n de los principios, fines y orientaciones generales que emanan de la presente ley. E) Convocar al Congreso Nacional de Educaci\u00f3n. F) Conformar comisiones de asesoramiento y estudio de distintas tem\u00e1ticas educativas. G) Crear las subcomisiones que considere pertinentes para el cumplimiento de sus fines, las que podr\u00e1n ser de car\u00e1cter permanente o transitorias. H) Informar a la ciudadan\u00eda sobre el grado de cumplimiento del Plan Nacional de Educaci\u00f3n.(*) "
}